dw_client/__init__.py
dw_client/__main__.py
dw_client/cli.py
dw_client/client.py
dw_client/config.py
dw_client/py.typed
dw_client/singleinstance.py
dw_client-0.0.3.dist-info/METADATA
dw_client-0.0.3.dist-info/WHEEL
dw_client-0.0.3.dist-info/entry_points.txt
dw_client-0.0.3.dist-info/top_level.txt
dw_client-0.0.3.dist-info/RECORD
