Metadata-Version: 2.1
Name: dw-client
Version: 0.0.3
Summary: Client library for DeskWatch
Home-page: https://deskwatch.net/
Author: Kohinoor Bharti
Author-email: kohinoorbharti7@gmail.com
License: UNKNOWN
Platform: UNKNOWN
Requires-Python: >=3.7,<4.0
Requires-Dist: dw-core (>=0.0.3)
Requires-Dist: click (<9.0,>=8.0)
Requires-Dist: persist-queue (<0.7.0,>=0.6.0)
Requires-Dist: requests (<3.0,>=2.22)
